setup.py
minimongo/__init__.py
minimongo/collection.py
minimongo/config.py
minimongo/index.py
minimongo/model.py
minimongo/options.py
minimongo.egg-info/PKG-INFO
minimongo.egg-info/SOURCES.txt
minimongo.egg-info/dependency_links.txt
minimongo.egg-info/not-zip-safe
minimongo.egg-info/requires.txt
minimongo.egg-info/top_level.txt
minimongo/tests/__init__.py
minimongo/tests/test_model.py
minimongo/tests/test_utils.py