Metadata-Version: 1.0
Name: minimongo
Version: 0.2.6
Summary: Minimal database Model management for MongoDB
Home-page: http://github.com/slacy/minimongo
Author: Steve Lacy
Author-email: slacy@slacy.com
License: UNKNOWN
Keywords: mongo,mongodb,pymongo,orm
Platform: any
Classifier: Development Status :: 3 - Alpha
Classifier: Intended Audience :: Developers
Classifier: Programming Language :: Python
Classifier: Topic :: Database
